Makefile
license.txt
scapegoat_mod.m4
scapegoat_mod.py
setup.py
test-scapegoat_mod
this-pylint
scapegoat_mod.egg-info/PKG-INFO
scapegoat_mod.egg-info/SOURCES.txt
scapegoat_mod.egg-info/dependency_links.txt
scapegoat_mod.egg-info/top_level.txt